{
  "weights": [
    {
      "id": 8099903,
      "value": 175,
      "dateTime": "2020-11-05T07:19:51.000-07:00",
      "isIrregular": false
    },
    {
      "id": 8099803,
      "value": 177.5684,
      "dateTime": "2020-11-08T15:01:51.000-07:00",
      "isIrregular": false
    },
    {
      "id": 7509826,
      "value": 178.8783,
      "dateTime": "2020-10-19T11:17:56.000-07:00",
      "isIrregular": false
    },
    {
      "id": 7450658,
      "value": 77.9234,
      "dateTime": "2020-09-30T14:27:19.000-07:00",
      "isIrregular": true
    },
    {
      "id": 7999551,
      "value": 179.1245,
      "dateTime": "2020-11-03T13:19:09.000-07:00",
      "isIrregular": false
    },
    {
      "id": 7606794,
      "value": 174.621125,
      "dateTime": "2020-10-22T08:30:06.000-07:00",
      "isIrregular": false
    },
    {
      "id": 7450656,
      "value": 56.189798453,
      "dateTime": "2020-10-17T12:50:47.000-07:00",
      "isIrregular": true
    },
    {
      "id": 7899240,
      "value": 180.4031458,
      "dateTime": "2020-10-31T08:53:38.000-07:00",
      "isIrregular": false
    },
    {
      "weightObj": {
        "id": "",
        "value": "",
        "dateTime": "",
        "isIrregular": ""
      },
      "id": 8099904
    },
    {
      "value": "13",
      "id": 8099905
    },
    {
      "value": "23",
      "id": 8099906
    },
    {
      "value": "23",
      "id": 8099907
    },
    {
      "value": "23",
      "id": 8099908
    },
    {
      "value": "23",
      "id": 8099909
    },
    {
      "id": 8099910
    },
    {
      "id": 8099911
    },
    {
      "value": "2333",
      "id": 8099912
    },
    {
      "weightObj": {
        "id": "",
        "value": "32",
        "dateTime": "",
        "isIrregular": ""
      },
      "id": 8099913
    },
    {
      "id": 8099914
    },
    {
      "weightObj": {
        "id": "",
        "value": "33",
        "dateTime": "",
        "isIrregular": ""
      },
      "id": 8099915
    },
    {
      "value": "33",
      "id": 8099916
    },
    {
      "value": "33",
      "dateTime": "",
      "id": 8099917
    },
    {
      "weightObj": {
        "id": "",
        "value": "33",
        "dateTime": "",
        "isIrregular": ""
      },
      "id": 8099918
    },
    {
      "weightObj": {
        "id": "",
        "value": "23",
        "dateTime": "",
        "isIrregular": ""
      },
      "id": 8099919
    },
    {
      "weightObj": {
        "id": "",
        "value": "11",
        "dateTime": "",
        "isIrregular": ""
      },
      "id": 8099920
    },
    {
      "weightObj": {
        "id": "",
        "value": "24",
        "dateTime": "",
        "isIrregular": ""
      },
      "id": 8099921
    },
    {
      "weightObj": {
        "id": "",
        "value": "344",
        "dateTime": "",
        "isIrregular": ""
      },
      "id": 8099922
    },
    {
      "weightObj": {
        "value": "3",
        "dateTime": "",
        "isIrregular": false
      },
      "id": 8099923
    },
    {
      "weightObj": {
        "value": "4",
        "isIrregular": false
      },
      "id": 8099924
    },
    {
      "weightObj": {
        "value": "4",
        "dateTime": "",
        "isIrregular": false
      },
      "id": 8099925
    },
    {
      "weightObj": {
        "value": "12",
        "isIrregular": false
      },
      "id": 8099926
    },
    {
      "weightObj": {
        "value": "343",
        "dateTime": "Feb 14, 4:00 PM",
        "isIrregular": false
      },
      "id": 8099927
    },
    {
      "value": "45",
      "dateTime": "Feb 14, 4:04 PM",
      "isIrregular": false,
      "id": 8099928
    },
    {
      "dateTime": "Feb 14, 4:23 PM",
      "isIrregular": false,
      "id": 8099929
    },
    {
      "value": "333",
      "dateTime": "Feb 14, 5:03 PM",
      "isIrregular": false,
      "id": 8099930
    },
    {
      "value": "12",
      "dateTime": "Feb 14, 5:07 PM",
      "isIrregular": false,
      "id": 8099931
    },
    {
      "value": "23",
      "dateTime": "Feb 14, 5:09 PM",
      "isIrregular": false,
      "id": 8099932
    },
    {
      "value": "3",
      "dateTime": "Feb 14, 5:09 PM",
      "isIrregular": false,
      "id": 8099933
    },
    {
      "value": "344",
      "dateTime": "Feb 14, 5:14 PM",
      "isIrregular": false,
      "id": 8099934
    },
    {
      "value": "34",
      "dateTime": "Feb 14, 5:15 PM",
      "isIrregular": false,
      "id": 8099935
    },
    {
      "value": "343",
      "dateTime": "Feb 14, 5:16 PM",
      "isIrregular": false,
      "id": 8099936
    },
    {
      "value": "23",
      "dateTime": "Feb 14, 5:20 PM",
      "isIrregular": false,
      "id": 8099937
    },
    {
      "value": "",
      "dateTime": "Feb 14, 5:24 PM",
      "isIrregular": false,
      "id": 8099938
    },
    {
      "value": "",
      "dateTime": "Feb 14, 5:24 PM",
      "isIrregular": false,
      "id": 8099939
    },
    {
      "value": "",
      "dateTime": "Feb 14, 5:24 PM",
      "isIrregular": false,
      "id": 8099940
    },
    {
      "value": "",
      "dateTime": "Feb 14, 5:24 PM",
      "isIrregular": false,
      "id": 8099941
    },
    {
      "value": "",
      "dateTime": "Feb 14, 5:24 PM",
      "isIrregular": false,
      "id": 8099942
    },
    {
      "value": "",
      "dateTime": "Feb 14, 5:24 PM",
      "isIrregular": false,
      "id": 8099943
    },
    {
      "value": "",
      "dateTime": "Feb 14, 5:24 PM",
      "isIrregular": false,
      "id": 8099944
    },
    {
      "value": "",
      "dateTime": "Feb 14, 5:24 PM",
      "isIrregular": false,
      "id": 8099945
    },
    {
      "value": "",
      "dateTime": "Feb 14, 5:24 PM",
      "isIrregular": false,
      "id": 8099946
    },
    {
      "value": "",
      "dateTime": "Feb 14, 5:24 PM",
      "isIrregular": false,
      "id": 8099947
    },
    {
      "value": "34",
      "dateTime": "Feb 14, 5:26 PM",
      "isIrregular": false,
      "id": 8099948
    },
    {
      "value": "3",
      "dateTime": "Feb 14, 5:28 PM",
      "isIrregular": false,
      "id": 8099949
    },
    {
      "dateTime": "Feb 14, 6:04 PM",
      "isIrregular": false,
      "id": 8099950
    },
    {
      "value": "",
      "dateTime": "Feb 14, 6:04 PM",
      "isIrregular": false,
      "id": 8099951
    }
  ]
}